{
    "범용형 부린": 0,
    "시제형 부린 MKⅡ": 0,
    "특장형 부린 MKIII": 0,
    "듀이 ": 0,
    "캐신": 0,
    "다운즈": 0,
    "그리들리": 0,
    "크레이븐": 0,
    "맥콜": 0,
    "모리": 0,
    "플레처": 0,
    "찰스 오스본": 1,
    "대처": 0,
    "얼릭": 0,
    "푸트": 0,
    "스펜스": 0,
    "벤슨": 0,
    "라피": 0,
    "심즈": 0,
    "허먼": 0,
    "엘드릿지": 0,
    "베일리": 0,
    "래드포드": 0,
    "젠킨스": 0,
    "니콜라스": 0,
    "부시": 0,
    "헤이즐우드": 0,
    "배시 ": 0,
    "하비": 0,
    "커크": 0,
    "킴벌리 ": 0,
    "멀라니 ": 0,
    "아일윈 ": 0,
    "스탠리 ": 0,
    "스몰리": 0,
    "할시 파웰": 0,
    "쿠퍼 ": 0,
    "알렌 M. 섬너": 1,
    "스테판 포터": 1,
    "모리슨": 1,
    "잉그레이엄": 0,
    "브리스톨": 1,
    "허먼Ⅱ": 1,
    "라피Ⅱ": 1,
    "벨": 1,
    "밀러": 1,
    "오마하": 0,
    "롤리": 0,
    "브루클린": 0,
    "피닉스": 0,
    "헬레나": 0,
    "애틀란타": 0,
    "쥬노": 0,
    "샌디에이고": 0,
    "클리블랜드": 0,
    "컬럼비아": 0,
    "리치몬드": 0,
    "호놀룰루": 0,
    "세인트루이스": 0,
    "몬트필리어 ": 0,
    "덴버 ": 0,
    "멤피스": 0,
    "콩코드 ": 0,
    "꼬마 헬레나 ": 0,
    "꼬마 클리블랜드 ": 0,
    "꼬마 샌디에이고 ": 0,
    "산후안 ": 0,
    "버밍햄 ": 0,
    "클리블랜드(μ장비)": 0,
    "빌럭시": 0,
    "리노 ": 0,
    "마블헤드 ": 1,
    "보이시": 1,
    "휴스턴Ⅱ": 1,
    "보이시(μ장비)": 0,
    "파고": 1,
    "산타페": 1,
    "펜사콜라": 0,
    "솔트레이크시티": 0,
    "노샘프턴": 0,
    "시카고": 0,
    "휴스턴": 0,
    "포틀랜드": 0,
    "인디애나폴리스": 0,
    "아스토리아": 0,
    "퀸시": 0,
    "빈센스": 0,
    "위치타": 0,
    "뉴올리언스": 0,
    "미니애폴리스": 0,
    "샌프란시스코": 1,
    "볼티모어 ": 1,
    "브레머튼": 1,
    "볼티모어(μ장비)": 0,
    "노샘프턴Ⅱ": 1,
    "루이빌": 1,
    "피츠버그": 1,
    "꼬마 앵커리지": 1,
    "컨스텔레이션": 1,
    "네바다": 0,
    "오클라호마": 0,
    "펜실베이니아": 1,
    "애리조나": 0,
    "테네시": 0,
    "캘리포니아": 0,
    "콜로라도": 0,
    "메릴랜드": 0,
    "웨스트버지니아": 0,
    "노스캐롤라이나": 0,
    "워싱턴": 0,
    "사우스다코타": 0,
    "인디애나": 1,
    "뉴저지": 1,
    "매사추세츠 ": 0,
    "앨라배마 ": 0,
    "롱 아일랜드": 0,
    "보그": 0,
    "카사블랑카 ": 1,
    "랭글리": 0,
    "렉싱턴": 0,
    "새러토가": 0,
    "레인저": 0,
    "요크타운": 0,
    "엔터프라이즈": 1,
    "호넷": 0,
    "와스프": 0,
    "에식스": 0,
    "요크타운Ⅱ": 1,
    "인트레피드 ": 1,
    "호넷Ⅱ": 1,
    "프랭클린": 1,
    "타이콘데로가": 1,
    "벙커힐 ": 0,
    "인디펜던스 ": 0,
    "프린스턴": 1,
    "랭글리Ⅱ": 1,
    "바탄 ": 0,
    "샌 재신토": 1,
    "샹그릴라 ": 0,
    "꼬마 엔터프라이즈": 1,
    "데이스": 0,
    "알바코어": 0,
    "카발라 ": 1,
    "블루길 ": 0,
    "알바코어(μ장비)": 0,
    "아처피시": 0,
    "노틸러스": 1,
    "플래셔": 1,
    "헤링": 1,
    "베스탈": 0,
    "괌": 1,
    "시애틀 ": 0,
    "조지아 ": 0,
    "앵커리지": 1,
    "키어사지": 1,
    "할포드": 1,
    "캔자스": 1,
    "아마존": 0,
    "아카스타": 0,
    "아덴트": 0,
    "비글": 0,
    "불독": 0,
    "코멧": 0,
    "크레센트": 0,
    "시그넷": 1,
    "폭스하운드": 0,
    "포춘": 0,
    "그렌빌 ": 0,
    "글로우웜": 0,
    "하디 ": 0,
    "헌터 ": 0,
    "재블린": 0,
    "주노": 0,
    "뱀파이어": 0,
    "주피터 ": 0,
    "저지": 0,
    "매치리스": 0,
    "머스킷티어": 0,
    "에코 ": 0,
    "에스키모 ": 1,
    "이카로스 ": 1,
    "저비스": 1,
    "재너스": 1,
    "히어로": 1,
    "누비안": 1,
    "트라팔가": 1,
    "갤런트": 1,
    "리엔더": 0,
    "아킬레스": 0,
    "에이잭스": 1,
    "다이도": 0,
    "사우스햄튼 ": 0,
    "셰필드": 0,
    "맨체스터": 1,
    "글로스터": 1,
    "에든버러": 0,
    "벨파스트": 0,
    "아레투사": 0,
    "갈라테아": 0,
    "오로라 ": 0,
    "피지": 0,
    "자메이카": 0,
    "꼬마 벨파스트": 0,
    "뉴캐슬": 0,
    "시리우스 ": 0,
    "퀴라소 ": 0,
    "컬루 ": 0,
    "스위프트슈어": 0,
    "블랙 프린스": 0,
    "셰필드(μ장비)": 0,
    "글래스고 ": 0,
    "허마이오니 ": 1,
    "다이도(μ장비)": 0,
    "페넬로피": 1,
    "카리브디스": 1,
    "벨로나": 1,
    "스킬라": 1,
    "리버풀": 1,
    "클레오파트라": 1,
    "트리니다드": 1,
    "런던": 0,
    "슈롭셔": 0,
    "켄트": 0,
    "서포크": 0,
    "노포크": 0,
    "도셋셔": 0,
    "요크": 0,
    "엑세터": 0,
    "서식스 ": 0,
    "꼬마 체셔": 1,
    "데본셔": 1,
    "리나운": 0,
    "리펄스": 0,
    "후드": 0,
    "꼬마 리나운 ": 1,
    "퀸 엘리자베스": 0,
    "워스파이트": 0,
    "넬슨": 0,
    "로드니": 0,
    "킹 조지 5세 ": 0,
    "프린스 오브 웨일즈": 1,
    "듀크 오브 요크": 1,
    "하우": 1,
    "밸리언트 ": 1,
    "리벤지": 1,
    "뱅가드": 1,
    "로열 오크": 1,
    "라이온급 전함 - 라이온": 1,
    "허미즈": 0,
    "아거스": 1,
    "유니콘": 0,
    "센토": 0,
    "체이서 ": 0,
    "퍼시어스 ": 1,
    "알비온": 1,
    "테세우스": 1,
    "이글 ": 1,
    "아크 로열": 1,
    "일러스트리어스": 0,
    "빅토리어스": 0,
    "포미더블 ": 1,
    "글로리어스": 0,
    "임플래커블": 1,
    "꼬마 일러스트리어스 ": 0,
    "일러스트리어스(μ장비)": 0,
    "인도미터블": 1,
    "꼬마 포미더블": 1,
    "포미더블(μ장비)": 0,
    "에레버스": 0,
    "테러": 0,
    "애버크롬비 ": 0,
    "넵튠": 0,
    "모나크": 1,
    "체셔 ": 1,
    "드레이크 ": 1,
    "플리머스": 1,
    "후부키": 1,
    "시라유키": 0,
    "미유키": 1,
    "아야나미": 0,
    "아카츠키": 0,
    "히비키 ": 0,
    "이카즈치": 0,
    "이나즈마": 0,
    "시라츠유": 0,
    "유다치": 0,
    "시구레": 0,
    "유키카제 ": 0,
    "카게로": 0,
    "시라누이": 0,
    "노와키": 0,
    "하츠하루 ": 0,
    "와카바": 0,
    "하츠시모": 0,
    "아리아케": 0,
    "유구레": 0,
    "쿠로시오": 0,
    "오야시오": 0,
    "시마카제": 1,
    "카미카제": 0,
    "마츠카제 ": 0,
    "무츠키": 0,
    "키사라기": 0,
    "우즈키": 0,
    "미나즈키": 0,
    "후미즈키 ": 0,
    "나가츠키 ": 0,
    "미카즈키": 0,
    "우미카제": 1,
    "야마카제": 1,
    "카와카제 ": 0,
    "키요나미 ": 0,
    "니이즈키": 0,
    "하루츠키 ": 0,
    "요이즈키 ": 0,
    "우라카제 ": 0,
    "이소카제 ": 0,
    "하마카제": 0,
    "타니카제": 0,
    "아사시오 ": 1,
    "오오시오 ": 0,
    "미치시오": 0,
    "아라시오 ": 0,
    "우라나미": 0,
    "하타카제 ": 0,
    "마키나미 ": 0,
    "카스미 ": 0,
    "하나즈키 ": 1,
    "나가나미 ": 0,
    "{namecode:27}": 1,
    "오이테": 0,
    "카자구모": 1,
    "와카츠키": 1,
    "하츠즈키": 1,
    "아사나기": 1,
    "스즈나미": 1,
    "유바리": 0,
    "나가라": 0,
    "이스즈": 0,
    "나토리": 1,
    "유라": 1,
    "키누": 0,
    "아부쿠마": 0,
    "모가미 ": 0,
    "미쿠마 ": 0,
    "센다이": 0,
    "진츠": 0,
    "나카 ": 1,
    "아가노": 0,
    "노시로 ": 0,
    "사카와": 1,
    "노시로(μ장비)": 0,
    "와타라세": 1,
    "아야세": 1,
    "후루타카": 0,
    "카코": 0,
    "아오바": 0,
    "키누가사": 0,
    "치쿠마": 1,
    "묘코": 0,
    "나치": 0,
    "아시가라 ": 0,
    "하구로": 1,
    "타카오": 0,
    "아타고": 0,
    "마야": 0,
    "{namecode:69}": 0,
    "스즈야": 0,
    "{namecode:60}": 0,
    "운젠": 1,
    "콘고 ": 0,
    "히에이": 0,
    "하루나 ": 0,
    "키리시마": 0,
    "아마기 ": 1,
    "꼬마 히에이 ": 0,
    "꼬마 아마기": 1,
    "콘고(μ장비)": 0,
    "후소": 0,
    "야마시로": 0,
    "이세": 0,
    "휴가": 0,
    "나가토 ": 0,
    "무츠 ": 0,
    "카가 ": 0,
    "토사 ": 1,
    "무사시": 1,
    "미카사": 0,
    "{namecode:80}": 1,
    "오와리": 1,
    "스루가 ": 1,
    "{namecode:85}": 0,
    "준요 ": 0,
    "호쇼": 0,
    "즈이호": 1,
    "쇼호": 0,
    "류조 ": 0,
    "류호 ": 1,
    "{namecode:103}": 0,
    "{namecode:104}": 0,
    "아카기": 0,
    "카가": 0,
    "소류": 0,
    "히류": 0,
    "쇼카쿠": 0,
    "즈이카쿠": 0,
    "다이호": 0,
    "{namecode:182}": 0,
    "꼬마 아카기 ": 0,
    "아카기(μ장비)": 0,
    "다이호(μ장비)": 0,
    "카츠라기": 1,
    "꼬마 다이호": 1,
    "꼬마 시나노": 1,
    "아마기(항공모함)": 1,
    "이19": 0,
    "이26": 0,
    "이58": 0,
    "이25 ": 0,
    "이56 ": 0,
    "이168 ": 0,
    "아카시": 0,
    "이13": 0,
    "{namecode:188}": 1,
    "이부키": 0,
    "이즈모": 0,
    "키타카제 ": 0,
    "아즈마 ": 0,
    "하쿠류": 1,
    "시만토": 1,
    "다이센": 1,
    "Z1": 0,
    "Z2": 0,
    "Z9": 1,
    "Z11": 1,
    "Z13": 1,
    "Z16": 1,
    "Z18": 0,
    "Z19": 0,
    "Z20": 0,
    "Z21": 0,
    "Z23": 0,
    "Z24": 1,
    "Z25": 0,
    "Z26": 0,
    "Z28": 0,
    "Z35": 0,
    "Z36": 0,
    "{namecode:537}": 1,
    "Z46": 0,
    "{namecode:494}": 1,
    "Z52": 1,
    "오토 폰 알벤슬레벤": 1,
    "쾨니히스베르크": 0,
    "카를스루에": 0,
    "쾰른": 0,
    "라이프치히": 0,
    "뉘른베르크": 1,
    "마그데부르크": 1,
    "엠덴": 1,
    "엘빙": 1,
    "레겐스부르크": 1,
    "뒤스부르크": 1,
    "아드미럴 히퍼": 0,
    "블뤼허": 1,
    "프린츠 오이겐": 0,
    "도이칠란트": 0,
    "아드미랄 그라프 슈피": 0,
    "아드미랄 히퍼(μ장비)": 0,
    "론(μ장비)": 0,
    "프린츠 하인리히": 1,
    "프린츠 아달베르트": 1,
    "요르크": 1,
    "꼬마 프린츠 오이겐": 1,
    "꼬마 슈피": 1,
    "프리드리히 카를": 1,
    "프린츠 오이겐(μ장비)": 0,
    "꼬마 에기르": 1,
    "샤른호르스트": 0,
    "그나이제나우": 0,
    "자이틀리츠": 1,
    "뤼초": 1,
    "브륀힐드": 1,
    "알비트": 1,
    "아드미랄 젠커": 1,
    "비스마르크 ": 0,
    "티르피츠": 0,
    "울리히 폰 후텐": 1,
    "튀링겐": 1,
    "비스마르크 Zwei": 1,
    "꼬마 프리드리히": 1,
    "베저": 0,
    "엘베": 1,
    "야드": 1,
    "그라프 체펠린": 0,
    "꼬마 그라프 체펠린 ": 0,
    "페터 슈트라서": 1,
    "프리츠 루메이": 1,
    "U-81": 0,
    "U-47": 0,
    "U-557": 0,
    "U-556": 0,
    "U-73": 0,
    "U-101": 0,
    "U-522": 0,
    "U-110": 0,
    "U-96": 1,
    "U-37": 1,
    "U-410": 0,
    "U-1206": 1,
    "{namecode:536}": 1,
    "U-552": 1,
    "론": 0,
    "프리드리히 데어 그로세 ": 0,
    "마인츠 ": 1,
    "오딘 ": 1,
    "에기르": 1,
    "아우구스트 폰 파르제팔": 0,
    "프린츠 루프레히트": 1,
    "펠릭스 슐츠": 1,
    "힌덴부르크": 1,
    "메클렌부르크": 1,
    "안샨 ": 0,
    "푸슌 ": 0,
    "창춘 ": 0,
    "타이위안 ": 0,
    "롱우": 1,
    "후번": 1,
    "페이윈": 1,
    "창펑": 1,
    "푸보": 1,
    "얏센 ": 0,
    "닝하이": 0,
    "핑하이": 0,
    "잉 루이": 1,
    "차오 호": 1,
    "하이티엔": 1,
    "하이치": 1,
    "지안": 1,
    "하이롱": 1,
    "지엔우": 1,
    "환창": 1,
    "젠하이": 1,
    "화지아": 1,
    "딩안": 1,
    "하얼빈": 1,
    "카라비니에레 ": 0,
    "빈첸초 조베르티": 0,
    "마에스트라레": 1,
    "리베치오": 1,
    "니콜로소 다 레코": 1,
    "폼페오 마뇨": 1,
    "알프레도 오리아니": 1,
    "에마누엘레 페사노": 1,
    "아틸리오 레골로": 1,
    "조수에 카르두치": 1,
    "두카 델리 아브루치": 1,
    "주세페 가리발디": 1,
    "바르톨로메오 콜레오니": 1,
    "트렌토 ": 1,
    "차라 ": 0,
    "폴라": 0,
    "트리에스테": 1,
    "볼차노": 1,
    "고리치아": 1,
    "비토리오 베네토": 1,
    "리토리오 ": 0,
    "로마": 1,
    "콘테 디 카보우르 ": 0,
    "줄리오 체사레 ": 0,
    "안드레아 도리아": 1,
    "라파엘로": 1,
    "아퀼라": 1,
    "임페로": 1,
    "토리첼리": 1,
    "레오나르도 다 빈치": 1,
    "마조레 바라카": 1,
    "마르코 폴로": 0,
    "나폴리": 1,
    "비토리오 쿠니베르티": 1,
    "그로즈니 ": 0,
    "민스크 ": 0,
    "타슈켄트 ": 0,
    "타슈켄트(μ장비)": 0,
    "스트례미텔니": 0,
    "그리먀시": 1,
    "그롬키": 1,
    "소브라지텔니": 1,
    "키예프": 1,
    "오그네보이": 1,
    "스비레피": 1,
    "아브로라 ": 0,
    "파먀티 메르쿠리야 ": 1,
    "차파예프 ": 1,
    "키로프": 1,
    "쿠이비셰프": 1,
    "무르만스크": 1,
    "보로실로프": 1,
    "올레그": 1,
    "탈린": 1,
    "쿠르스크": 1,
    "강구트 ": 1,
    "소비에츠키 소유즈": 1,
    "소비에츠카야 벨로루시아": 1,
    "소비에츠카야 러시아 ": 1,
    "아르한겔스크": 1,
    "세바스토폴": 1,
    "폴타바": 1,
    "카잔": 1,
    "볼가": 1,
    "크론시타트": 1,
    "치칼로프": 1,
    "아드미랄 나히모프": 1,
    "드미트리 돈스코이": 1,
    "르 트리옹팡 ": 0,
    "포르뱅 ": 0,
    "르 테메레르": 0,
    "로피니아트르 ": 0,
    "르 아르디": 1,
    "르 테리블": 1,
    "마이예 브레제": 1,
    "르 테메레르(μ장비)": 0,
    "에밀 베르탱 ": 0,
    "잔 다르크 ": 1,
    "기샹": 1,
    "뒤게 트루앵": 1,
    "쉬프랑": 1,
    "브렌누스": 1,
    "뒤켄": 1,
    "마세나": 1,
    "리슐리외 ": 1,
    "리옹": 1,
    "알자스": 1,
    "부아 벨루": 1,
    "베아른 ": 0,
    "팽르베": 1,
    "쉬르쿠프 ": 0,
    "생 루이": 0,
    "샹파뉴 ": 0,
    "브레스트": 1,
    "바야르": 1,
    "르 마르스 ": 0,
    "타르투 ": 1,
    "보클랭 ": 1,
    "케르생": 1,
    "플뢰레": 1,
    "에페": 1,
    "모가도르": 1,
    "르 말랭 ": 1,
    "르 말랭(μ장비)": 1,
    "랭동타블": 1,
    "로데슈": 1,
    "라 갈리소니에르 ": 1,
    "마르세예즈": 1,
    "포슈": 1,
    "알제리 ": 1,
    "듀플렉스": 1,
    "됭케르크 ": 0,
    "스트라스부르": 1,
    "장 바르 ": 1,
    "클레망소": 1,
    "가스코뉴(μ장비)": 1,
    "조프르": 1,
    "가스코뉴 ": 1,
    "플랑드르": 1,
    "에버트센": 1,
    "드 제번 프로빈시엔": 1,
    "하우덴 리우": 1,
    "로열 포춘": 1,
    "상 마르티뉴": 1,
    "골든 하인드": 1,
    "메리 셀러스트": 1,
    "위다": 1,
    "어드벤처 갤리": 1,
    "건스웨이": 1,
    "팬시": 1,
    "아미티": 1,
    "포츠머스 어드벤처": 1,
    "돌핀": 1,
    "헌터·META": 0,
    "포춘·META": 0,
    "하타카제·META": 0,
    "킴벌리·META": 0,
    "뱀파이어·META": 0,
    "카스미·META": 0,
    "그렌빌·META": 0,
    "카와카제·META": 0,
    "헬레나·META": 0,
    "멤피스·META": 0,
    "셰필드·META": 0,
    "라 갈리소니에르·META": 0,
    "진츠·META": 0,
    "키로프·META": 0,
    "파먀티 메르쿠리야·META": 0,
    "트렌토·META": 0,
    "알제리·META": 0,
    "포슈·META": 0,
    "위치타·META": 0,
    "아드미랄 히퍼·META": 0,
    "볼차노·META": 0,
    "그나이제나우·META": 0,
    "샤른호르스트·META": 0,
    "리펄스·META": 0,
    "리나운·META": 0,
    "히에이·META": 0,
    "됭케르크·META": 0,
    "후소·META": 0,
    "야마시로·META": 0,
    "애리조나·META": 0,
    "퀸 엘리자베스·META": 0,
    "로드니·META": 0,
    "나가토·META": 0,
    "줄리오 체사레·META": 0,
    "안드레아 도리아·META": 0,
    "네바다·META": 0,
    "히요·META": 0,
    "준요·META": 0,
    "프린스턴·META": 0,
    "호쇼·META": 0,
    "히류·META": 0,
    "아크 로열·META": 0,
    "소류·META": 0,
    "베아른·META": 0,
    "다이호·META": 0,
    "호넷·META": 0,
    "글로리어스·META": 0,
    "U-556·META": 0,
    "베스탈·META": 0,
    "에레버스·META": 0,
    "느와르": 0,
    "블랑": 0,
    "퍼플 하트": 0,
    "블랙 하트": 0,
    "화이트 하트": 0,
    "그린 하트": 0,
    "키즈나 아이 ": 0,
    "키즈나 아이·Elegant": 0,
    "키즈나 아이·Anniversary": 0,
    "키즈나 아이·SuperGamer": 0,
    "시라카미 후부키": 0,
    "토키노 소라": 0,
    "미나토 아쿠아": 0,
    "나츠이로 마츠리": 0,
    "나키리 아야메": 0,
    "무라사키 시온": 0,
    "오오카미 미오": 0,
    "마리 로즈": 0,
    "호노카": 0,
    "카스미": 0,
    "미사키": 0,
    "나기사": 0,
    "뇨텐구": 0,
    "모니카": 0,
    "루나": 1,
    "타마키": 1,
    "아마미 하루카": 1,
    "키사라기 치하야": 1,
    "미나세 이오리": 1,
    "미우라 아즈사": 1,
    "아키즈키 리츠코": 1,
    "후타미 아미": 1,
    "후타미 마미": 1,
    "타카라다 릿카": 1,
    "신죠 아카네": 1,
    "핫스": 1,
    "나미코": 1,
    "미나미 유메": 1,
    "아스카가와 치세": 1,
    "무지나": 1,
    "2대": 1,
    "공주": 1,
    "라이잘린 스타우트": 1,
    "클라우디아 발렌츠": 1,
    "파트리샤 아벨하임": 1,
    "릴라 디자이어스": 1,
    "세리 글로스": 1,
    "칼라 이데아스": 1,
    "아스카": 1,
    "이카루가": 1,
    "호무라": 1,
    "유미": 1,
    "무라사키": 1,
    "유우야키": 1,
    "라라 사타린 데빌룩": 1,
    "나나 아스타 데빌룩": 1,
    "모모 베리아 데빌룩": 1,
    "금빛 어둠": 1,
    "사이렌지 하루나": 1,
    "코테가와 유이": 1,
    "BLACK★ROCK SHOOTER": 1,
    "DEAD MASTER": 1,
    "유미아 리스펠트": 1,
    "아일라 폰 뒤러": 1,
    "니나 프리드": 1,
    "레이냐": 1
}